karoosync.py
karoosync-1.4.0.dist-info/LICENSE
karoosync-1.4.0.dist-info/METADATA
karoosync-1.4.0.dist-info/WHEEL
karoosync-1.4.0.dist-info/entry_points.txt
karoosync-1.4.0.dist-info/top_level.txt
karoosync-1.4.0.dist-info/RECORD
