Metadata-Version: 2.1
Name: karoosync
Version: 1.4.0
Summary: Syncs workouts from intervals.icu to Hammerhead Karoo
Home-page: https://github.com/bakermat/karoosync
Author: Bakermat
Author-email: 
License: MIT
Platform: UNKNOWN
License-File: LICENSE
Requires-Dist: requests (>=2.26)
Requires-Dist: PyJWT
